{
  "runId": "run-policy-gates-c-1773246198",
  "planId": "umbrella.plan.policy-multi-agent-gates.v1",
  "state": "SUCCEEDED",
  "createdAt": "2026-03-11T16:23:19.482416+00:00",
  "updatedAt": "2026-03-11T16:23:19.574499+00:00",
  "terminalReason": "all_steps_succeeded",
  "steps": [
    {
      "stepId": "priv-memory-write",
      "status": "SUCCESS",
      "attemptCount": 1,
      "startedAt": "2026-03-11T16:23:19.569463+00:00",
      "endedAt": "2026-03-11T16:23:19.573730+00:00",
      "result": {
        "ok": true,
        "exitCode": 0,
        "result": {
          "status": "SUCCESS",
          "kind": "memoryWrite",
          "memory": {
            "namespace": "team",
            "key": "policy-gates-shared",
            "value": {
              "ok": true
            },
            "metadata": {
              "agentId": "external-agent-1773246198"
            },
            "updatedAt": "2026-03-11T16:23:19.571401+00:00"
          }
        },
        "stderr": "",
        "command": [
          "memory-core",
          "put"
        ]
      }
    }
  ],
  "services": {
    "policy": "http://127.0.0.1:56786",
    "lifecycle": "http://127.0.0.1:56787",
    "router": "http://127.0.0.1:56788",
    "scheduler": "http://127.0.0.1:56789",
    "execution": "http://127.0.0.1:56790",
    "approval": "http://127.0.0.1:56791",
    "orchestrator": "local"
  },
  "finishedAt": "2026-03-11T16:23:19.574502+00:00"
}
