{
  "runId": "run-umbrella04-approval-run-status-1773237156",
  "planId": "umbrella.plan.approval-run-status-smoke.v1",
  "state": "SUCCEEDED",
  "createdAt": "2026-03-11T13:52:37.893504+00:00",
  "updatedAt": "2026-03-11T13:52:38.034214+00:00",
  "terminalReason": "all_steps_succeeded",
  "steps": [
    {
      "stepId": "approval-gated-step",
      "status": "SUCCESS",
      "attemptCount": 1,
      "startedAt": "2026-03-11T13:52:37.982232+00:00",
      "endedAt": "2026-03-11T13:52:38.033362+00:00",
      "result": {
        "ok": true,
        "exitCode": 0,
        "result": {
          "runId": "run-umbrella04-approval-run-status-1773237156",
          "stepId": "approval-gated-step",
          "status": "SUCCESS",
          "exitCode": 0,
          "startedAt": "2026-03-11T13:52:38.012352+00:00",
          "endedAt": "2026-03-11T13:52:38.030242+00:00",
          "stdout": "approval-run-status-ok\n",
          "stderr": ""
        },
        "stderr": "",
        "command": [
          "/Users/coolfriend/desktop/umbrella0.3/umbrella0.4/scripts/adapters/removed-runtime-adapter",
          "--umbrella-root",
          "/Users/coolfriend/desktop/umbrella0.3/umbrella0.4",
          "submit_step",
          "--run-id",
          "run-umbrella04-approval-run-status-1773237156",
          "--step-id",
          "approval-gated-step",
          "--command",
          "python3 -c 'print(\"approval-run-status-ok\")'",
          "--workdir",
          ".",
          "--timeout-sec",
          "30"
        ]
      },
      "approvalKey": "umbrella04-approval-run-status-key"
    }
  ],
  "services": {
    "policy": "http://127.0.0.1:53911",
    "lifecycle": "http://127.0.0.1:53912",
    "router": "http://127.0.0.1:53913",
    "scheduler": "http://127.0.0.1:53914",
    "execution": "http://127.0.0.1:53915",
    "approval": "http://127.0.0.1:53916",
    "orchestrator": "local"
  },
  "finishedAt": "2026-03-11T13:52:38.034218+00:00"
}
